adparser/Parser.py
adparser/__init__.py
adparser/AST/ASTree.py
adparser/AST/__init__.py
adparser/AST/Blocks/BlockIterator.py
adparser/AST/Blocks/Blocks.py
adparser/AST/Blocks/Enums.py
adparser/AST/Blocks/__init__.py
adparser/AST/Scaners/HTMLScaner.py
adparser/AST/Scaners/Scaner.py
adparser/AST/Scaners/__init__.py
adparser/Visitors/Selectors.py
adparser/Visitors/Visitor.py
adparser/Visitors/__init__.py
adparser-0.1.6.dist-info/METADATA
adparser-0.1.6.dist-info/WHEEL
adparser-0.1.6.dist-info/licenses/LICENSE
adparser-0.1.6.dist-info/RECORD
