Metadata-Version: 2.4
Name: adparser
Version: 0.1.6
Summary: The adparser library for Python provides powerful capabilities for working with AsciiDoc documents
Project-URL: Homepage, https://github.com/fertcool/AsciiDocParse
Project-URL: Issues, https://github.com/fertcool/AsciiDocParse/issues
Author-email: Artem Ivashchenko <fertcool@gmail.com>
License-File: LICENSE
Classifier: Development Status :: 4 - Beta
Classifier: License :: OSI Approved :: MIT License
Classifier: Operating System :: MacOS
Classifier: Operating System :: Microsoft :: Windows
Classifier: Operating System :: POSIX :: Linux
Classifier: Programming Language :: Python :: 3
Requires-Python: >=3.10
Requires-Dist: lxml
